fusion_tests/__init__.py
fusion_tests/fsnAllTickets.py
fusion_tests/fsnAssetNameToAssetInfo.py
fusion_tests/fsnAssetToRawTimeLock.py
fusion_tests/fsnBlockheight.py
fusion_tests/fsnBuyTicket.py
fusion_tests/fsnCreateAsset.py
fusion_tests/fsnCreateRawAsset.py
fusion_tests/fsnCreateSmartContract.py
fusion_tests/fsnGenNotation.py
fusion_tests/fsnGetAllSwaps.py
fusion_tests/fsnGetAllTimelockInfo.py
fusion_tests/fsnGetAsset.py
fusion_tests/fsnGetBalance.py
fusion_tests/fsnGetTimelockInfo.py
fusion_tests/fsnGetTransaction.py
fusion_tests/fsnInc_and_DecRawAsset.py
fusion_tests/fsnLockedInAssetInfo.py
fusion_tests/fsnMakeAndRecallRawSwap.py
fusion_tests/fsnOfflineTransactions.py
fusion_tests/fsnSendAsset.py
fusion_tests/fsnSendFSN.py
fusion_tests/fsnSendRawAsset.py
fusion_tests/fsnSendRawAsset_toUSAN.py
fusion_tests/fsnSendRawFSN.py
fusion_tests/fsnSendToRawTimeLock.py
fusion_tests/fsnTakeRawSwap.py
fusion_tests/fsnTicketsByAddress.py
fusion_tests/fsnTimeLockToRawTimeLock.py
fusion_tests/fsnToAndFromRawTimeLock.py
web3fsnpy/__init__.py
web3fsnpy/fsn.py
web3fsnpy/eth_account/__init__.py
web3fsnpy/eth_account/account.py
web3fsnpy/eth_account/datastructures.py
web3fsnpy/eth_account/messages.py
web3fsnpy/eth_account/_utils/__init__.py
web3fsnpy/eth_account/_utils/signing.py
web3fsnpy/eth_account/_utils/transactions.py
web3fsnpy/eth_account/_utils/validation.py
web3fsnpy/eth_account/_utils/structured_data/__init__.py
web3fsnpy/eth_account/_utils/structured_data/hashing.py
web3fsnpy/eth_account/_utils/structured_data/validation.py
web3fsnpy/eth_account/signers/__init__.py
web3fsnpy/eth_account/signers/base.py
web3fsnpy/eth_account/signers/local.py
web3fsnpy/fusion/ERC20_contract_addresses.py
web3fsnpy/fusion/__init__.py
web3fsnpy/fusion/exceptions.py
web3fsnpy/fusion/fsn_api.py
web3fsnpy/fusion/fsn_assets.py
web3fsnpy/fusion/fsn_swaps.py
web3fsnpy/fusion/fsn_tickets.py
web3fsnpy/fusion/fsn_timelocks.py
web3fsnpy/fusion/fsn_transactions.py
web3fsnpy/fusion/fsn_utils.py
web3fsnpy-1.0.2.dist-info/LICENSE
web3fsnpy-1.0.2.dist-info/METADATA
web3fsnpy-1.0.2.dist-info/WHEEL
web3fsnpy-1.0.2.dist-info/top_level.txt
web3fsnpy-1.0.2.dist-info/RECORD
