Metadata-Version: 2.1
Name: web3fsnpy
Version: 1.0.2
Summary: A Fusion extension to the web3.py package
Home-page: https://github.com/FUSIONFoundation/web3fsnpy
Author: Marcel Cure
Author-email: marcel.cure@gmail.com
License: UNKNOWN
Keywords: Fusion Protocol,blockchain,Decentralized finance
Platform: UNKNOWN
Classifier: Programming Language :: Python :: 3
Classifier: License :: OSI Approved :: MIT License
Classifier: Operating System :: OS Independent
Classifier: Programming Language :: Python :: 3.7
Classifier: Natural Language :: English
Requires-Python: >=3.6
Requires-Dist: attrdict (==2.0.1)
Requires-Dist: attrs (==19.1.0)
Requires-Dist: base58 (==1.0.3)
Requires-Dist: certifi (==2019.9.11)
Requires-Dist: chardet (==3.0.4)
Requires-Dist: cytoolz (==0.10.1)
Requires-Dist: eth-abi (==2.0.0)
Requires-Dist: eth-hash (==0.2.0)
Requires-Dist: eth-keyfile (==0.5.1)
Requires-Dist: eth-keys (==0.2.4)
Requires-Dist: eth-rlp (==0.1.2)
Requires-Dist: hexbytes (==0.2.0)
Requires-Dist: idna (==2.8)
Requires-Dist: ipfshttpclient (==0.4.12)
Requires-Dist: jsonschema (==3.0.2)
Requires-Dist: lru-dict (==1.1.6)
Requires-Dist: multiaddr (==0.0.8)
Requires-Dist: netaddr (==0.7.19)
Requires-Dist: parsimonious (==0.8.1)
Requires-Dist: protobuf (==3.10.0)
Requires-Dist: pycryptodome (==3.9.0)
Requires-Dist: pyrsistent (==0.15.4)
Requires-Dist: python-dateutil (==2.8.0)
Requires-Dist: requests (==2.22.0)
Requires-Dist: rlp (==1.1.0)
Requires-Dist: six (==1.12.0)
Requires-Dist: toolz (==0.10.0)
Requires-Dist: urllib3 (==1.25.6)
Requires-Dist: varint (==1.0.2)
Requires-Dist: web3 (==5.5.0)
Requires-Dist: websockets (==8.1.0)
